bpe_tokenizer/__init__.py
bpe_tokenizer/bpe_tokenizer.py
bpe_tokenizer/sanitizer.py
python_bpe_tokenizer-0.2.0.dist-info/METADATA
python_bpe_tokenizer-0.2.0.dist-info/WHEEL
python_bpe_tokenizer-0.2.0.dist-info/entry_points.txt
python_bpe_tokenizer-0.2.0.dist-info/top_level.txt
python_bpe_tokenizer-0.2.0.dist-info/RECORD
