Metadata-Version: 2.1
Name: python-bpe-tokenizer
Version: 0.2.0
Summary: Python based BPE Tokenizer
Author: jafarmahin
Author-email: jafarmahin107@gmail.com
Classifier: Programming Language :: Python :: 3
Classifier: License :: OSI Approved :: MIT License
Classifier: Operating System :: OS Independent
Requires-Python: >=3.6
Requires-Dist: transformers
Requires-Dist: flask
Requires-Dist: tqdm
